MANIFEST.in
README.rst
setup.cfg
setup.py
mongo_mq.egg-info/PKG-INFO
mongo_mq.egg-info/SOURCES.txt
mongo_mq.egg-info/dependency_links.txt
mongo_mq.egg-info/requires.txt
mongo_mq.egg-info/top_level.txt
mongo_mq.egg-info/zip-safe
mongomq/__init__.py
mongomq/lock.py
mongomq/mongomq.py
mongomq/test.py
mongomq/utils.py