Metadata-Version: 1.0
Name: mongo-mq
Version: 0.0.1
Summary: A queue using mongo as backend storage.
Home-page: https://github.com/dzaytsev91/mongomq
Author: Zaytsev Dmithry
Author-email: zaytsev_dmitriy@aol.com
License: BSD-derived
Platform: UNKNOWN
